astroskies/__init__.py
astroskies/settings.py
astroskies/urls.py
astroskies/wsgi.py
astroskies/base/__init__.py
astroskies/base/urls.py
astroskies/base/views.py
astroskies/base/__pycache__/__init__.cpython-310.pyc
astroskies/base/__pycache__/views.cpython-310.pyc
astroskies/base/management/__init__.py
astroskies/base/management/__pycache__/__init__.cpython-310.pyc
astroskies/base/management/commands/__init__.py
astroskies/base/management/commands/initadmin.py
astroskies-0.1.1.dist-info/AUTHORS.txt
astroskies-0.1.1.dist-info/LICENSE.txt
astroskies-0.1.1.dist-info/METADATA
astroskies-0.1.1.dist-info/WHEEL
astroskies-0.1.1.dist-info/top_level.txt
astroskies-0.1.1.dist-info/RECORD
