Metadata-Version: 2.1
Name: astroskies
Version: 0.1.1
Summary: Demo project to learn Django Dockerization
Home-page: https://github.com/urtzai/astroskies
Author: Urtzi Odriozola
Author-email: uodriozola@codesyntax.com
License: MIT
Platform: UNKNOWN
Classifier: Development Status :: 4 - Beta
Classifier: Environment :: Web Environment
Classifier: Framework :: Django
Classifier: Intended Audience :: Developers
Classifier: License :: OSI Approved :: MIT License
Classifier: Operating System :: OS Independent
Classifier: Programming Language :: Python
Classifier: Programming Language :: Python :: 3
Classifier: Programming Language :: Python :: 3.8
Classifier: Programming Language :: Python :: 3.9
Classifier: Programming Language :: Python :: 3.10
Classifier: Programming Language :: Python :: Implementation :: PyPy
Classifier: Topic :: Internet :: WWW/HTTP
License-File: LICENSE.txt
License-File: AUTHORS.txt
Requires-Dist: django
